isecycle/ISE_adaptive_card.j2
isecycle/ISE_csv.j2
isecycle/ISE_graph_csv.j2
isecycle/ISE_html.j2
isecycle/ISE_md.j2
isecycle/ISE_mermaid_class.j2
isecycle/ISE_mermaid_flowchart.j2
isecycle/ISE_mermaid_relationship.j2
isecycle/ISE_mermaid_state.j2
isecycle/ISE_mindmap.j2
isecycle/ISE_mp3.j2
isecycle/ISE_text.j2
isecycle/__init__.py
isecycle/datatable_footer.j2
isecycle/datatable_header.j2
isecycle/isecycle.py
isecycle/mnt_version.py
isecycle/script.py
isecycle-1.0.3.dist-info/entry_points.txt
isecycle-1.0.3.dist-info/LICENSE
isecycle-1.0.3.dist-info/WHEEL
isecycle-1.0.3.dist-info/METADATA
isecycle-1.0.3.dist-info/RECORD
