Metadata-Version: 2.1
Name: isecycle
Version: 1.0.3
Summary: Business Ready Documents from Cisco Identity Services Engine
Author: John Capobianco
Author-email: ptcapo@gmail.com
Requires-Python: >=3.8,<4.0
Classifier: Programming Language :: Python :: 3
Classifier: Programming Language :: Python :: 3.10
Classifier: Programming Language :: Python :: 3.8
Classifier: Programming Language :: Python :: 3.9
Requires-Dist: CairoSVG (>=2.5.2,<3.0.0)
Requires-Dist: Jinja2 (>=3.1.2,<4.0.0)
Requires-Dist: PyYAML (>=6.0,<7.0)
Requires-Dist: gTTS (>=2.2.4,<3.0.0)
Requires-Dist: networkx (>=2.8.4,<3.0.0)
Requires-Dist: pandas (>=1.4.3,<2.0.0)
Requires-Dist: pyvis (>=0.2.1,<0.3.0)
Requires-Dist: requests (>=2.28.0,<3.0.0)
Requires-Dist: requests-toolbelt (>=0.9.1,<0.10.0)
Requires-Dist: rich (>=12.4.4,<13.0.0)
Requires-Dist: rich-click (>=1.5.1,<2.0.0)
Requires-Dist: xmltodict (>=0.13.0,<0.14.0)
